README.md
setup.py
ailabkit/__init__.py
ailabkit/cli.py
ailabkit/config.py
ailabkit.egg-info/PKG-INFO
ailabkit.egg-info/SOURCES.txt
ailabkit.egg-info/dependency_links.txt
ailabkit.egg-info/requires.txt
ailabkit.egg-info/top_level.txt
ailabkit/agent/__init__.py
ailabkit/agent/cli.py
ailabkit/agent/core.py
ailabkit/agent/prompts.py
ailabkit/agent/tools.py
ailabkit/agent/web.py
ailabkit/agent/agents/__init__.py
ailabkit/agent/agents/calculator.py
ailabkit/agent/agents/converter.py
ailabkit/agent/agents/datetime_tools.py
ailabkit/agent/agents/dictionary.py
ailabkit/agent/agents/education_tools.py
ailabkit/agent/agents/text_tools.py
ailabkit/agent/commands/__init__.py
ailabkit/agent/commands/ask.py
ailabkit/agent/commands/interactive.py
ailabkit/agent/commands/tools.py
ailabkit/agent/commands/web.py
ailabkit/agent/tools/__init__.py
ailabkit/agent/tools/calculator.py
ailabkit/agent/tools/search.py
ailabkit/agent/tools/weather.py
ailabkit/chat/__init__.py
ailabkit/chat/bots.py
ailabkit/chat/cli.py
ailabkit/chat/get_response.py
ailabkit/chat/personalities.py
ailabkit/chat/commands/__init__.py
ailabkit/chat/commands/ask.py
ailabkit/chat/commands/bots.py
ailabkit/chat/commands/doctor.py
ailabkit/chat/commands/interactive.py
ailabkit/chat/commands/web.py
ailabkit/chat/personalities/__init__.py
ailabkit/chat/personalities/creative.py
ailabkit/chat/personalities/educational.py
ailabkit/chat/personalities/friendly.py
ailabkit/chat/personalities/sarcastic.py
ailabkit/chat/personalities/technical.py
ailabkit/chat/personalities/template.py
ailabkit/chat/personalities/therapeutic.py
ailabkit/chat/personalities/bots/__init__.py
ailabkit/chat/personalities/bots/coder_bot.py
ailabkit/chat/personalities/bots/friendly_bot.py
ailabkit/chat/personalities/bots/pirate_bot.py
ailabkit/chat/personalities/bots/sarcastic_bot.py
ailabkit/chat/personalities/bots/shakespeare_bot.py
ailabkit/chat/personalities/bots/teacher_bot.py
ailabkit/chat/personalities/bots/template_bot.py
ailabkit/commands/__init__.py
ailabkit/commands/config.py
ailabkit/commands/doctor.py
ailabkit/commands/list.py
ailabkit/commands/version.py
ailabkit/data/__init__.py
