Metadata-Version: 2.1
Name: ailabkit
Version: 0.1.0
Summary: AI Learning Lab Toolkit for classrooms
Home-page: https://github.com/teaching-repositories/ailabkit
Author: Michael Borck
Author-email: michael@borck.me
License: UNKNOWN
Platform: UNKNOWN
Classifier: Programming Language :: Python :: 3
Classifier: License :: OSI Approved :: MIT License
Classifier: Operating System :: OS Independent
